discmoji/__init__.py
discmoji/_http.py
discmoji/app_info.py
discmoji/bot.py
discmoji/channel.py
discmoji/command.py
discmoji/context.py
discmoji/emoji.py
discmoji/errors.py
discmoji/gateway.py
discmoji/guild.py
discmoji/intents.py
discmoji/member.py
discmoji/message.py
discmoji/messagesubtypes.py
discmoji/overwrites.py
discmoji/py.typed
discmoji/roles.py
discmoji/team.py
discmoji/types.py
discmoji/user.py
discmoji/cli/__init__.py
discmoji/cli/_cli.py
discmoji/cli/commands.py
discmoji/cli/utils.py
discmoji-0.2.33.dist-info/LICENSE
discmoji-0.2.33.dist-info/METADATA
discmoji-0.2.33.dist-info/WHEEL
discmoji-0.2.33.dist-info/top_level.txt
discmoji-0.2.33.dist-info/RECORD
