Metadata-Version: 2.1
Name: discmoji
Version: 0.2.33
Summary: A discord API wrapper.
Author: mojidev-py, XenonPy
License: MIT
Project-URL: github, https://github.com/mojidev-py/discmoji/
Keywords: API,wrapper,discord,library
Classifier: Development Status :: 5 - Production/Stable
Classifier: Programming Language :: Python :: 3
Classifier: Operating System :: OS Independent
Classifier: Typing :: Typed
Requires-Python: >=3.8
License-File: LICENSE
Requires-Dist: asyncio
Requires-Dist: aiohttp
